{
  "tasks": [
    {
      "id": 13,
      "task_name": "weerr",
      "startTime": "1:00 AM",
      "endTime": "1:09 AM"
    },
    {
      "id": 14,
      "task_name": "task 123",
      "startTime": "3:00 AM",
      "endTime": "9:00 AM"
    },
    {
      "id": 15,
      "task_name": "gfhg",
      "startTime": "11:15 AM",
      "endTime": "5:00 AM"
    },
    {
      "id": 16,
      "task_name": "jghj",
      "startTime": "11:16 AM",
      "endTime": "11:25 AM"
    },
    {
      "id": 17,
      "task_name": "ghrfh",
      "startTime": "1:09 AM",
      "endTime": "4:20 AM"
    },
    {
      "id": 18,
      "task_name": "grfdg",
      "startTime": "2:00 AM",
      "endTime": "3:00 AM"
    },
    {
      "id": 19,
      "task_name": "vvbchd",
      "startTime": "12:15 AM",
      "endTime": "1:20 AM"
    },
    {
      "id": 20,
      "task_name": "hgy",
      "startTime": "10:25 AM",
      "endTime": "5:30 AM"
    },
    {
      "id": 21,
      "task_name": "tgds",
      "startTime": "9:20 AM",
      "endTime": "11:20 AM"
    },
    {
      "id": 22,
      "task_name": "rdtt5",
      "startTime": "10:10 AM",
      "endTime": "1:00 AM"
    },
    {
      "id": 23,
      "task_name": "fgd",
      "startTime": "11:22 AM",
      "endTime": "1:00 AM"
    },
    {
      "id": 24,
      "task_name": "saaaa",
      "startTime": "11:50 AM",
      "endTime": "3:00 AM"
    }
  ]
}